.hgignore
CHANGES.txt
LICENSE.txt
README.txt
bootstrap.py
buildout.cfg
setup.py
js/__init__.py
js.jquery_validation_engine.egg-info/PKG-INFO
js.jquery_validation_engine.egg-info/SOURCES.txt
js.jquery_validation_engine.egg-info/dependency_links.txt
js.jquery_validation_engine.egg-info/entry_points.txt
js.jquery_validation_engine.egg-info/namespace_packages.txt
js.jquery_validation_engine.egg-info/not-zip-safe
js.jquery_validation_engine.egg-info/requires.txt
js.jquery_validation_engine.egg-info/top_level.txt
js/jquery_validation_engine/__init__.py
js/jquery_validation_engine/test_jquery-validation-engine.txt
js/jquery_validation_engine/resources/README.txt
js/jquery_validation_engine/resources/jquery.validationEngine-cz.js
js/jquery_validation_engine/resources/jquery.validationEngine-da.js
js/jquery_validation_engine/resources/jquery.validationEngine-de.js
js/jquery_validation_engine/resources/jquery.validationEngine-en.js
js/jquery_validation_engine/resources/jquery.validationEngine-es.js
js/jquery_validation_engine/resources/jquery.validationEngine-fr.js
js/jquery_validation_engine/resources/jquery.validationEngine-it.js
js/jquery_validation_engine/resources/jquery.validationEngine-ja.js
js/jquery_validation_engine/resources/jquery.validationEngine-nl.js
js/jquery_validation_engine/resources/jquery.validationEngine-pl.js
js/jquery_validation_engine/resources/jquery.validationEngine-pt.js
js/jquery_validation_engine/resources/jquery.validationEngine-ro.js
js/jquery_validation_engine/resources/jquery.validationEngine-ru.js
js/jquery_validation_engine/resources/jquery.validationEngine-tr.js
js/jquery_validation_engine/resources/jquery.validationEngine.js