Metadata-Version: 1.0
Name: js.jquery-validation-engine
Version: 2.2
Summary: Fanstatic packaging of jQuery-Validation-Engine
Home-page: UNKNOWN
Author: Fanstatic Developers
Author-email: fanstatic@googlegroups.com
License: BSD
Platform: UNKNOWN
